panels/__init__.py
panels/bardell.cp313-win_amd64.pyd
panels/bardell.pyx
panels/legendre_gauss_quadrature.cp313-win_amd64.pyd
panels/legendre_gauss_quadrature.pyx
panels/logger.py
panels/modelDB.py
panels/plot_shell.py
panels/shell.py
panels/shell_fext.py
panels/version.py
panels/core/include/bardell.hpp
panels/core/include/bardell_functions.hpp
panels/core/include/legendre_gauss_quadrature.hpp
panels/core/src/bardell.cpp
panels/core/src/bardell_functions.cpp
panels/core/src/legendre_gauss_quadrature.cpp
panels/core/src/legendre_gauss_quadrature_304.cpp
panels/dev/__init__.py
panels/dev/matrixtools.py
panels/models/__init__.py
panels/models/clpt_bardell_field.cp313-win_amd64.pyd
panels/models/clpt_bardell_field.pyx
panels/models/cylshell_clpt_donnell_bardell.cp313-win_amd64.pyd
panels/models/cylshell_clpt_donnell_bardell.pyx
panels/models/cylshell_clpt_donnell_bardell_num.cp313-win_amd64.pyd
panels/models/cylshell_clpt_donnell_bardell_num.pyx
panels/models/plate_clpt_donnell_bardell.cp313-win_amd64.pyd
panels/models/plate_clpt_donnell_bardell.pyx
panels/models/plate_clpt_donnell_bardell_num.cp313-win_amd64.pyd
panels/models/plate_clpt_donnell_bardell_num.pyx
panels/multidomain/__init__.py
panels/multidomain/cylinder.py
panels/multidomain/cylinder_blade_stiffened.py
panels/multidomain/multidomain.py
panels/multidomain/tstiff2d_1stiff_compression.py
panels/multidomain/tstiff2d_1stiff_flutter.py
panels/multidomain/tstiff2d_1stiff_freq.py
panels/multidomain/connections/__init__.py
panels/multidomain/connections/kCBFxcte.cp313-win_amd64.pyd
panels/multidomain/connections/kCBFycte.cp313-win_amd64.pyd
panels/multidomain/connections/kCSB.cp313-win_amd64.pyd
panels/multidomain/connections/kCSB_dmg.cp313-win_amd64.pyd
panels/multidomain/connections/kCSSxcte.cp313-win_amd64.pyd
panels/multidomain/connections/kCSSycte.cp313-win_amd64.pyd
panels/multidomain/connections/kCpd.cp313-win_amd64.pyd
panels/multidomain/connections/penalties.py
panels/stiffener/__init__.py
panels-0.5.0.dist-info/licenses/LICENSE
panels-0.5.0.dist-info/METADATA
panels-0.5.0.dist-info/WHEEL
panels-0.5.0.dist-info/top_level.txt
panels-0.5.0.dist-info/RECORD
