Metadata-Version: 2.1
Name: panels
Version: 0.5.0
Summary: Semi-analytical models for plates, shells and stiffened panels
Home-page: https://github.com/saullocastro/panels
Author: Saullo G. P. Castro, Nathan D'Souza
Author-email: S.G.P.Castro@tudelft.nl
License: 3-Clause BSD
Keywords: Ritz method,semi-analyticalEnergy-based method,structural analysis,structural optimization,static analysis,buckling,vibration,panel flutter,structural dynamics,implicit time integration,explicit time integration
Classifier: Development Status :: 4 - Beta
Classifier: Intended Audience :: Education
Classifier: Intended Audience :: Science/Research
Classifier: Intended Audience :: Developers
Classifier: Intended Audience :: End Users/Desktop
Classifier: Topic :: Scientific/Engineering
Classifier: Topic :: Scientific/Engineering :: Mathematics
Classifier: Topic :: Education
Classifier: Topic :: Software Development
Classifier: Topic :: Software Development :: Libraries :: Python Modules
Classifier: Operating System :: Microsoft :: Windows
Classifier: Operating System :: Unix
Classifier: Operating System :: POSIX :: BSD
Classifier: Programming Language :: Python :: 3.8
Classifier: Programming Language :: Python :: 3.9
Classifier: Programming Language :: Python :: 3.10
Classifier: Programming Language :: Python :: 3.11
Classifier: Programming Language :: Python :: 3.12
Classifier: Programming Language :: Python :: 3.13
Requires-Python: >=3.8
License-File: LICENSE
